hidos/__init__.py
hidos/__main__.py
hidos/_version.py
hidos/archive.py
hidos/cache.py
hidos/cli.py
hidos/dsi.py
hidos/dulwich.py
hidos/dulwish.py
hidos/exceptions.py
hidos/git.py
hidos/history.py
hidos/py.typed
hidos/remote.py
hidos/repo.py
hidos/util.py
hidos-2.6.1.dist-info/LICENSE
hidos-2.6.1.dist-info/METADATA
hidos-2.6.1.dist-info/WHEEL
hidos-2.6.1.dist-info/entry_points.txt
hidos-2.6.1.dist-info/top_level.txt
hidos-2.6.1.dist-info/RECORD
