Metadata-Version: 2.1
Name: hidos
Version: 2.6.1
Summary: Hash Identifed Digital Object Successions
Author-email: Castedo Ellerman <castedo@castedo.com>
License: MIT License
Project-URL: Homepage, https://hidos.readthedocs.io/
Project-URL: Repository, https://gitlab.com/perm.pub/hidos
Keywords: git
Classifier: Programming Language :: Python :: 3
Classifier: License :: OSI Approved :: MIT License
Classifier: Operating System :: POSIX
Requires-Python: >=3.11.4
License-File: LICENSE
Requires-Dist: dulwich >=0.22.6
Requires-Dist: platformdirs
Requires-Dist: requests
Requires-Dist: requests-cache
Requires-Dist: sshsig >=0.3
Provides-Extra: git
Requires-Dist: GitPython ; extra == 'git'
